tai_core_flask/__init__.py
tai_core_flask/environment_detector.py
tai_core_flask/flask_helper.py
tai_core_flask/environments/__init__.py
tai_core_flask/environments/azure_nb_environment.py
tai_core_flask/environments/base_environment.py
tai_core_flask/environments/credentialed_vm_environment.py
tai_core_flask/environments/databricks_environment.py
tai_core_flask/environments/local_ipython_environment.py
tai_core_flask/environments/public_vm_environment.py
tai_core_flask-0.7.8.dist-info/LICENSE
tai_core_flask-0.7.8.dist-info/METADATA
tai_core_flask-0.7.8.dist-info/WHEEL
tai_core_flask-0.7.8.dist-info/top_level.txt
tai_core_flask-0.7.8.dist-info/RECORD
