Metadata-Version: 2.1
Name: tai_core_flask
Version: 0.7.8
Summary: Trustworthy AI Core Flask Wrapper
Home-page: 
Author: AL360°
Author-email: developer@affectlog.com
Classifier: Programming Language :: Python :: 3.7
Classifier: Programming Language :: Python :: 3.8
Classifier: Programming Language :: Python :: 3.9
Classifier: Programming Language :: Python :: 3.10
Classifier: Programming Language :: Python :: 3.11
Classifier: License :: OSI Approved :: MIT License
Classifier: Operating System :: OS Independent
License-File: LICENSE
Requires-Dist: Flask
Requires-Dist: Flask-Cors
Requires-Dist: flask-socketio
Requires-Dist: greenlet>=1.1.2
Requires-Dist: gevent>=21.12.0
Requires-Dist: ipython<=7.16.3; python_version <= "3.6"
Requires-Dist: ipython>=7.31.1; python_version > "3.6"
Provides-Extra: dev
